cam2text/__init__.py
cam2text/core.py
cam2text/models/MobileNetSSD_deploy.caffemodel
cam2text/models/MobileNetSSD_deploy.prototxt.txt
cam2text-0.1.1.dist-info/licenses/LICENSE
cam2text-0.1.1.dist-info/METADATA
cam2text-0.1.1.dist-info/WHEEL
cam2text-0.1.1.dist-info/top_level.txt
cam2text-0.1.1.dist-info/RECORD
